humanthermalmodel/__init__.py
humanthermalmodel/arterialmodel.py
humanthermalmodel/body_data.csv
humanthermalmodel/coldmodel.py
humanthermalmodel/energybalanceequations.py
humancoldmodel-0.0.13.dist-info/LICENSE
humancoldmodel-0.0.13.dist-info/METADATA
humancoldmodel-0.0.13.dist-info/WHEEL
humancoldmodel-0.0.13.dist-info/top_level.txt
humancoldmodel-0.0.13.dist-info/RECORD
