Metadata-Version: 2.1
Name: humancoldmodel
Version: 0.0.13
Summary: A multi-segmented human bioheat model for cold and extremely cold exposures.
Home-page: https://github.com/zhushaohz
Author: zhushaohz
Author-email: zhushaohz@gmail.com
Project-URL: Bug Tracker, https://github.com/zhushaohz/
Classifier: Development Status :: 3 - Alpha
Classifier: Intended Audience :: Education
Classifier: Intended Audience :: Science/Research
Classifier: License :: OSI Approved :: GNU General Public License (GPL)
Classifier: Operating System :: OS Independent
Classifier: Programming Language :: Python :: 3
Classifier: Programming Language :: Python :: 3.8
Classifier: Topic :: Software Development :: Libraries :: Python Modules
Classifier: Topic :: Utilities
Requires-Python: >=3.8
License-File: LICENSE
Requires-Dist: pandas
Requires-Dist: numpy
Requires-Dist: scipy
Requires-Dist: solartotr
Requires-Dist: matplotlib
